naam/__init__.py
naam-0.1.1.dist-info/DESCRIPTION.rst
naam-0.1.1.dist-info/METADATA
naam-0.1.1.dist-info/RECORD
naam-0.1.1.dist-info/WHEEL
naam-0.1.1.dist-info/metadata.json
naam-0.1.1.dist-info/top_level.txt
