Metadata-Version: 2.0
Name: naam
Version: 0.1.1
Summary: Truly pythonic argument parser.
Home-page: https://github.com/puhitaku/naam
Author: Takumi Sueda
Author-email: puhitaku@gmail.com
License: MIT License
Platform: UNKNOWN
Classifier: Development Status :: 3 - Alpha
Classifier: Environment :: Console
Classifier: Intended Audience :: Developers
Classifier: License :: OSI Approved :: MIT License
Classifier: Operating System :: OS Independent
Classifier: Programming Language :: Python
Classifier: Programming Language :: Python :: 3
Classifier: Programming Language :: Python :: 3.6
Classifier: Topic :: Software Development :: User Interfaces
